<?xml version="1.0"?>
<musiccollection>
<album>
<jukeboxnumber>1</jukeboxnumber>
<mediatype>CD</mediatype>
<musiccategory>Rock</musiccategory>
<artist>Aerosmith</artist>
<title>Permanent Vacation</title>
<recordlabel>Geffen</recordlabel>
<coverart>01permvac.jpg</coverart>
<recordingyear>1987</recordingyear>
<cost>0.00</cost>
<track number="1">
<title>Heart's Done Time</title>
<length>4:42</length>
</track>
<track number="2">
<title>Magic Touch</title>
<length>4:40</length>
</track>
<track number="3">
<title>Rag Doll</title>
<length>4:21</length>
</track>
<track number="4">
<title>Simoriah</title>
<length>3:21</length>
</track>
<track number="5">
<title>Dude (Looks Like a Lady)</title>
<length>4:23</length>
</track>
<track number="6">
<title>St. John</title>
<length>4:12</length>
</track>
<track number="7">
<title>Hangman Jury</title>
<length>5:33</length>
</track>
<track number="8">
<title>Girl Keeps Coming Apart</title>
<length>4:12</length>
</track>
<track number="9">
<title>Angel</title>
<length>5:10</length>
</track>
<track number="10">
<title>Permanent Vacation</title>
<length>4:52</length>
</track>
<track number="11">
<title>I'm Down</title>
<length>2:20</length>
</track>
<track number="12">
<title>The Movie</title>
<length>4:00</length>
</track>
</album>
<album>
<jukeboxnumber>5</jukeboxnumber>
<mediatype>CD</mediatype>
<musiccategory>Rock</musiccategory>
<artist>Dire Straits</artist>
<title>Love Over Gold</title>
<recordlabel>Warner Bros</recordlabel>
<coverart>05direstraits.jpg</coverart>
<recordingyear>1982</recordingyear>
<cost>0.00</cost>
<track number="1">
<title>Telegraph Road</title>
<length>14:15</length>
</track>
<track number="2">
<title>Private Investigations</title>
<length>6:45</length>
</track>
<track number="3">
<title>Industrial Disease</title>
<length>5:49</length>
</track>
<track number="4">
<title>Love Over Gold</title>
<length>6:16</length>
</track>
<track number="5">
<title>It Never Rains</title>
<length>7:54</length>
</track>
</album>
<album>
<jukeboxnumber>7</jukeboxnumber>
<mediatype>CD</mediatype>
<musiccategory>Rock</musiccategory>
<artist>Dire Straits</artist>
<title>Money For Nothing</title>
<recordlabel>1988</recordlabel>
<coverart>07direstraits.jpg</coverart>
<recordingyear>1988</recordingyear>
<cost>0.00</cost>
<track number="1">
<title>Sultans Of Swing</title>
<length>5:46</length>
</track>
<track number="2">
<title>Down To The Waterline</title>
<length>4:00</length>
</track>
<track number="3">
<title>Portobello Belle - Live</title>
<length>4:33</length>
</track>
<track number="4">
<title>Twisting By The Pool</title>
<length>3:30</length>
</track>
<track number="5">
<title>Tunnel Of Love</title>
<length>8:09</length>
</track>
<track number="6">
<title>Romeo And Juliet</title>
<length>5:57</length>
</track>
<track number="7">
<title>Where Do You Think You're Going</title>
<length>3:31</length>
</track>
<track number="8">
<title>Walk Of Life</title>
<length>4:07</length>
</track>
<track number="9">
<title>Private Investigations</title>
<length>5:48</length>
</track>
<track number="10">
<title>Telegraph Road - Live</title>
<length>12:00</length>
</track>
<track number="11">
<title>Money For Nothing</title>
<length>4:05</length>
</track>
<track number="12">
<title>Brothers In Arms</title>
<length>4:48</length>
</track>
</album>
<album>
<jukeboxnumber>199</jukeboxnumber>
<mediatype>CD</mediatype>
<musiccategory>Classical</musiccategory>
<artist>Various</artist>
<title>Fantasia Disc 1</title>
<recordlabel>Buena Vista</recordlabel>
<coverart>199fantasia.jpg</coverart>
<recordingyear>1990</recordingyear>
<cost>0.00</cost>
<track number="1">
<title>Toccata and Fugue In D Minor (Bach) 
</title>
<LENGTH/>
</track>
<track number="2">
<title>Dance of the Sugar Plum Fairy  
(Tchaikovsky)</title>
<length>2:41</length>
</track>
<track number="3">
<title>Chinese Dance (Tchaikovsky)</title>
<length>1:02</length>
</track>
<track number="4">
<title>Dance of the Reed Flutes</title>
<length>1:48</length>
</track>
<track number="5">
<title>Arabian Dance (Tchaikovsky)</title>
<length>3:18</length>
</track>
<track number="6">
<title>Russian Dance (Tchaikovsky)</title>
<length>1:04</length>
</track>
<track number="7">
<title>Waltz of the Flowers (Tchaikovsky) 
</title>
<length>4:25</length>
</track>
<track number="8">
<title>The Sorcerer's Apprentice (Dukas) 
</title>
<length>9:17</length>
</track>
<track number="9">
<title>Rite of Spring (Stravinsky)</title>
<length>22:28</length>
</track>
</album>
<album>
<jukeboxnumber>200</jukeboxnumber>
<mediatype>CD</mediatype>
<musiccategory>Classical</musiccategory>
<artist>Various</artist>
<title>Fantasia Disc 2</title>
<recordlabel>Buena Vista</recordlabel>
<coverart>200fantasia.jpg</coverart>
<recordingyear>1990</recordingyear>
<cost>0.00</cost>
<track number="1">
<title>Symphony No. 6 I Allegro ma non  
troppo (Beethoven)</title>
<length>4:40</length>
</track>
<track number="2">
<title>Symphony No. 6 II Andante molto  
mosso (Beethoven)</title>
<length>6:23</length>
</track>
<track number="3">
<title>Symphony No. 6 III,IV,V Allegro  
(Beethoven)</title>
<length>10:57</length>
</track>
<track number="4">
<title>Dance of the Hours (Ponchielli) 
</title>
<length>12:13</length>
</track>
<track number="5">
<title>A Night On Bald Mountain (Mussorgsky) 
</title>
<length>7:25</length>
</track>
<track number="6">
<title>Ave Maria, Op. 52 No. 6 (Schubert) 
</title>
<length>6:27</length>
</track>
</album>
<album>
<jukeboxnumber>68</jukeboxnumber>
<mediatype>CD</mediatype>
<musiccategory>Hard Rock</musiccategory>
<artist>AC/DC</artist>
<title>Back In Black</title>
<recordlabel>Atlantic</recordlabel>
<coverart>68acdc.jpg</coverart>
<recordingyear>1980</recordingyear>
<cost>0.00</cost>
<track number="1">
<title>Hells Bells</title>
<length>5:09</length>
</track>
<track number="2">
<title>Shoot To Thrill</title>
<length>5:14</length>
</track>
<track number="3">
<title>What Do You Do For Money Honey</title>
<length>3:33</length>
</track>
<track number="4">
<title>Given The Dog A Bone</title>
<length>3:30</length>
</track>
<track number="5">
<title>Let Me Put My Love Into You</title>
<length>4:12</length>
</track>
<track number="7">
<title>You Shook Me All Night Long</title>
<length>3:28</length>
</track>
<track number="8">
<title>Have A Drink On Me</title>
<length>3:57</length>
</track>
<track number="9">
<title>Shake A Leg</title>
<length>4:03</length>
</track>
<track number="10">
<title>Rock and Roll Ain't Noise Pollution 
</title>
<length>4:12</length>
</track>
</album>
</musiccollection>